{"name":"AntoSid","symbol":"ANSD","logoURI":"https://raw.githubusercontent.com/gotchhan/AntoSid/main/logo.png","decimals":9,"address":"89fVzH7zgQoGpi8US3LGchvfc4tNP4vksYjW3dQ9Go8H","chainId":103,"tags":["change-the-world"],"extensions":{"website":"https://github.com/gotchhan/AntoSid","bridgeContract":null,"assetContract":null,"explorer":null,"twitter":null,"github":null,"medium":null,"tgann":null,"tggroup":null,"discord":null,"serumV3Usdt":null,"serumV3Usdc":null,"coingeckoId":null,"imageUrl":null,"description":null}}