{"name":"DNSmate Token","symbol":"DNSM","logoURI":"https://raw.githubusercontent.com/cybster/crypto-dnsm/main/logo.png","decimals":0,"address":"3bPDfM2QBf1a1is1kvjgzDGdwbVLczoa6dfuvGy7NXWT","chainId":101,"tags":["social-token","utility-token","community-token","altcoin"],"extensions":{"website":"https://coin.dnsmate.net","bridgeContract":null,"assetContract":null,"explorer":null,"twitter":null,"github":null,"medium":null,"tgann":null,"tggroup":null,"discord":null,"serumV3Usdt":null,"serumV3Usdc":null,"coingeckoId":null,"imageUrl":null,"description":"DNSmate token"}}