{"name":"Ottercoin","symbol":"Otter","logoURI":"https://cdn.jsdelivr.net/gh/ottercoin11/ottercoin/logo.png","decimals":9,"address":"3oLpKntC8W9AxiFhafRGBeALGuKdimduUXVPo1GQNHuX","chainId":101,"tags":["meme-token"],"extensions":{"website":"https://ottercoin.info/","bridgeContract":null,"assetContract":null,"explorer":null,"twitter":"https://twitter.com/ottercoinn","github":null,"medium":null,"tgann":null,"tggroup":null,"discord":"https://discord.gg/gXymhAfceY","serumV3Usdt":null,"serumV3Usdc":null,"coingeckoId":null,"imageUrl":null,"description":null}}