{"name":"Monster Inu","symbol":"INU","logoURI":"https://raw.githubusercontent.com/solana-labs/token-list/main/assets/mainnet/45HfvXJHY9msY2i4EmUpume1mSMLUvdaWsJRbctAobQM/logo.png","decimals":0,"address":"45HfvXJHY9msY2i4EmUpume1mSMLUvdaWsJRbctAobQM","chainId":101,"tags":["meme-token","metaverse"],"extensions":{"website":"https://inu.monster","bridgeContract":null,"assetContract":null,"explorer":null,"twitter":"https://twitter.com/inumonster","github":null,"medium":null,"tgann":null,"tggroup":null,"discord":null,"serumV3Usdt":null,"serumV3Usdc":null,"coingeckoId":null,"imageUrl":null,"description":null}}