{"name":"Synapse","symbol":"Synapse","logoURI":"https://arweave.net/h5NOMoLgFKGBZGOkipic6XFRBdCi7PKWLf5qtm-urzg?ext=png","decimals":9,"address":"58nQHy4ACJksBm5FfprDrPAR5bu1Rkgm4bwCPs2H2pQp","chainId":101,"tags":null,"extensions":{"website":null,"bridgeContract":null,"assetContract":null,"explorer":null,"twitter":"https://twitter.com/plsandtybased","github":null,"medium":null,"tgann":null,"tggroup":null,"discord":null,"serumV3Usdt":null,"serumV3Usdc":null,"coingeckoId":null,"imageUrl":null,"description":null}}