{"name":"Minty Whitelist","symbol":"MINTYWL","logoURI":"https://raw.githubusercontent.com/MintyAutomation/minty-logo/main/logo.png","decimals":0,"address":"5bwwZ41kzLWAZy1MqKttc5GW2vrE42hZ49EbJg6dpxSV","chainId":101,"tags":["whitelist-token"],"extensions":{"website":null,"bridgeContract":null,"assetContract":null,"explorer":null,"twitter":"https://twitter.com/MintyAutomation","github":null,"medium":null,"tgann":null,"tggroup":null,"discord":null,"serumV3Usdt":null,"serumV3Usdc":null,"coingeckoId":null,"imageUrl":null,"description":null}}