{"name":"rayTICKET-SOL LP Token","symbol":"rayTICKET-SOL","logoURI":"https://raw.githubusercontent.com/solana-labs/token-list/main/assets/mainnet/5HF5GxkFT8QcurPAygeTejS7Mikut7JuxLpwmP7uTXX7/logo.jpg","decimals":8,"address":"5HF5GxkFT8QcurPAygeTejS7Mikut7JuxLpwmP7uTXX7","chainId":101,"tags":["lp-token"],"extensions":{"website":"https://theticket.finance","bridgeContract":null,"assetContract":null,"explorer":null,"twitter":"https://twitter.com/TheTicketSol","github":null,"medium":null,"tgann":null,"tggroup":null,"discord":null,"serumV3Usdt":null,"serumV3Usdc":null,"coingeckoId":null,"imageUrl":null,"description":null,"telegram":"https://t.me/theticketfinance"}}