{"name":"APEC","symbol":"APEC","logoURI":"https://raw.githubusercontent.com/solana-labs/token-list/main/assets/mainnet/5MoDJmq3JqsNnottRdot3WHmhmD6h8VRodqsBKVu9LPk/logo.png","decimals":6,"address":"5MoDJmq3JqsNnottRdot3WHmhmD6h8VRodqsBKVu9LPk","chainId":101,"tags":["DeFi","meme-token"],"extensions":{"website":"https://apecoin.money","bridgeContract":null,"assetContract":null,"explorer":null,"twitter":"https://twitter.com/apeccoin","github":null,"medium":null,"tgann":null,"tggroup":null,"discord":null,"serumV3Usdt":null,"serumV3Usdc":null,"coingeckoId":null,"imageUrl":null,"description":null}}