{"name":"Click Token","symbol":"CLK","logoURI":"https://raw.githubusercontent.com/ilov-eu/assets/main/click-icon.png","decimals":9,"address":"5UH5K1sMfG6MszrqGAsWym1Q1q87akGVW9HXjD4SXcgn","chainId":101,"tags":["utility-token"],"extensions":{"website":"https://click.ilov.eu","bridgeContract":null,"assetContract":null,"explorer":null,"twitter":null,"github":null,"medium":null,"tgann":null,"tggroup":null,"discord":null,"serumV3Usdt":null,"serumV3Usdc":null,"coingeckoId":null,"imageUrl":null,"description":null}}