{"name":"Sol Merge AI","symbol":"SOLMERGE","logoURI":"https://raw.githubusercontent.com/solana-labs/token-list/main/assets/mainnet/5WLNynnq9pVio8Rj8XnqdZLYZSsaKzzAzS4aFvUK1tU2/logo.png","decimals":6,"address":"5WLNynnq9pVio8Rj8XnqdZLYZSsaKzzAzS4aFvUK1tU2","chainId":101,"tags":["solmergeaicom"],"extensions":{"website":"https://solmergeai.com","bridgeContract":null,"assetContract":null,"explorer":null,"twitter":null,"github":null,"medium":null,"tgann":null,"tggroup":null,"discord":null,"serumV3Usdt":null,"serumV3Usdc":null,"coingeckoId":null,"imageUrl":null,"description":null}}