{"name":"TheSolanDAO","symbol":"SDO","logoURI":"https://thesolandao.com/logohero.png","decimals":5,"address":"7SZUnH7H9KptyJkUhJ5L4Kee5fFAbqVgCHvt7B6wg4Xc","chainId":101,"tags":["social-token"],"extensions":{"website":"https://thesolandao.com","bridgeContract":null,"assetContract":null,"explorer":null,"twitter":"https://twitter.com/TheSolanDAO","github":null,"medium":null,"tgann":null,"tggroup":null,"discord":"https://discord.gg/d8z7TAz5WB","serumV3Usdt":null,"serumV3Usdc":null,"coingeckoId":"thesolandao","imageUrl":null,"description":null,"reddit":"https://www.reddit.com/r/TheSolanDAO"}}