{"name":"WipeMyAss","symbol":"WIPE","logoURI":"https://cdn.jsdelivr.net/gh/rxrxrxrx/WipeMyAss/wipemyass.jpg","decimals":9,"address":"9ae76zqD3cgzR9gvf5Thc2NN3ACF7rqqnrLqxNzgcre6","chainId":101,"tags":["community-token","meme-token","doge","dogecoin","solcum","monkey","woof","soldoge","samo","smb"],"extensions":{"website":"https://wipemyass.io/","bridgeContract":null,"assetContract":null,"explorer":null,"twitter":"https://twitter.com/WipeMyAssNFT","github":null,"medium":null,"tgann":null,"tggroup":null,"discord":null,"serumV3Usdt":null,"serumV3Usdc":"3kuUc5eTZyi7qajuFfDMMUUkqreEkUKtxQbVCjdriKVz","coingeckoId":"wipemyass","imageUrl":null,"description":null}}