{"name":"Orca Aquafarm Token (COPE/USDC[aquafarm])","symbol":"COPE/USDC","logoURI":"https://raw.githubusercontent.com/solana-labs/token-list/main/assets/mainnet/9SDpBrfqNxjXcCzpKWM6yUKdfky975VJBD6xcu5cKf5s/logo.svg","decimals":6,"address":"9SDpBrfqNxjXcCzpKWM6yUKdfky975VJBD6xcu5cKf5s","chainId":101,"tags":["lp-token"],"extensions":{"website":"https://www.orca.so","bridgeContract":null,"assetContract":null,"explorer":null,"twitter":"https://twitter.com/orca_so","github":null,"medium":null,"tgann":null,"tggroup":null,"discord":null,"serumV3Usdt":null,"serumV3Usdc":null,"coingeckoId":null,"imageUrl":null,"description":null}}