{"name":"Dalmatiancoin","symbol":"DAL","logoURI":"https://raw.githubusercontent.com/solana-labs/token-list/main/assets/mainnet/AnyCsr1VCBZcwVAxbKPuHhKDP5DQQSnRxGAo4ycgRMi2/logo.png","decimals":9,"address":"AnyCsr1VCBZcwVAxbKPuHhKDP5DQQSnRxGAo4ycgRMi2","chainId":101,"tags":null,"extensions":{"website":"https://dalmatiancoin.org/","bridgeContract":null,"assetContract":null,"explorer":null,"twitter":"https://twitter.com/coindalmatian","github":null,"medium":null,"tgann":null,"tggroup":null,"discord":null,"serumV3Usdt":null,"serumV3Usdc":null,"coingeckoId":null,"imageUrl":null,"description":null}}