{"name":"Aurory","symbol":"AURY","logoURI":"https://raw.githubusercontent.com/solana-labs/token-list/main/assets/mainnet/AURYydfxJib1ZkTir1Jn1J9ECYUtjb6rKQVmtYaixWPP/logo.png","decimals":9,"address":"AURYydfxJib1ZkTir1Jn1J9ECYUtjb6rKQVmtYaixWPP","chainId":101,"tags":["utility-token"],"extensions":{"website":"https://aurory.io","bridgeContract":null,"assetContract":null,"explorer":null,"twitter":null,"github":null,"medium":null,"tgann":null,"tggroup":null,"discord":null,"serumV3Usdt":null,"serumV3Usdc":null,"coingeckoId":"aurory","imageUrl":null,"description":"Aurory Token"}}