{"name":"BONES Token","symbol":"BONES","logoURI":"https://raw.githubusercontent.com/solana-labs/token-list/main/assets/mainnet/bonegFPgrpZ4bfVn3kQK1aMbGYddWtfMAywNt5LsuVE/logo.png","decimals":2,"address":"bonegFPgrpZ4bfVn3kQK1aMbGYddWtfMAywNt5LsuVE","chainId":101,"tags":["utility-token"],"extensions":{"website":"https://souldogs.city/","twitter":"https://twitter.com/SoulDogsNFT","medium":"https://medium.com/@souldogscity","discord":"https://discord.gg/souldogs","instagram":"https://www.instagram.com/souldogscity/"}}