{"name":"Crowny token","symbol":"CRWNY","logoURI":"https://raw.githubusercontent.com/solana-labs/token-list/main/assets/mainnet/CRWNYkqdgvhGGae9CKfNka58j6QQkaD5bLhKXvUYqnc1/logo.png","decimals":6,"address":"CRWNYkqdgvhGGae9CKfNka58j6QQkaD5bLhKXvUYqnc1","chainId":101,"tags":null,"extensions":{"website":"https://crowny.io/","bridgeContract":null,"assetContract":null,"explorer":null,"twitter":"https://twitter.com/crownyio","github":null,"medium":"https://crowny.medium.com/","tgann":null,"tggroup":null,"discord":"https://www.discord.gg/4JvMHrgNvv","serumV3Usdt":null,"serumV3Usdc":"H8GSFzSZmPNs4ANW9dPd5XTgrzWkta3CaT57TgWYs7SV","coingeckoId":"crowny-token","imageUrl":null,"description":null,"telegram":"https://t.me/crownyofficial"}}