{"name":"LCD-SAMO","symbol":"LCD-SAMO","logoURI":"https://raw.githubusercontent.com/solana-labs/token-list/main/assets/mainnet/CXbhgErBXhKiTJu95dK1aaoHukrg1Ghn8N2Spda7wSV/logo.svg","decimals":9,"address":"CXbhgErBXhKiTJu95dK1aaoHukrg1Ghn8N2Spda7wSV","chainId":101,"tags":["utility-token"],"extensions":{"website":"https://www.crazydice.app","bridgeContract":null,"assetContract":null,"explorer":null,"twitter":"https://twitter.com/CrazyDiceApp","github":null,"medium":null,"tgann":null,"tggroup":null,"discord":null,"serumV3Usdt":null,"serumV3Usdc":null,"coingeckoId":null,"imageUrl":null,"description":null,"telegram":"https://t.me/crazydiceapp"}}