{"name":"Moons","symbol":"FLRP","logoURI":"https://raw.githubusercontent.com/StarboyB/cryptologos/main/moons.png","decimals":6,"address":"D8wmkqGKpJvai2kScsFvK1n6uZMDicHKW6Zk6S53MRqU","chainId":101,"tags":["utility-token","metaverse","NFT-Gaming","game-token","game-currency","Gaming"],"extensions":{"twitter":"https://twitter.com/flatlinerp","discord":"https://www.discord.io/flatlinerp","description":"FlatlineRP is a Stylized GTA V roleplay server where players can play in a community based city with their own virtual characters.","instagram":"https://www.instagram.com/flatlinerp/","reddit":"https://www.reddit.com/r/flatline_rp/","facebook":"https://www.facebook.com/Flatline-RP-102075495648442"}}