{"name":"Katana MSOL Covered Call Vault Share","symbol":"kcMSOL","logoURI":"https://raw.githubusercontent.com/Katana-Labs/assets/master/token-list/E2eevzN2TBWAL1LiALAfEYFLRBzSDLugLjiNuZg9ehwT/logo.png","decimals":9,"address":"E2eevzN2TBWAL1LiALAfEYFLRBzSDLugLjiNuZg9ehwT","chainId":101,"tags":["Katana","share-token","utility-token"],"extensions":{"website":"https://app.katana.so","twitter":"https://twitter.com/Katana_HQ","github":"https://github.com/Katana-Labs","discord":"https://discord.gg/katana-hq"}}