{"name":"Skelly Gang Utillity Token","symbol":"SKELLY","logoURI":"https://raw.githubusercontent.com/solana-labs/token-list/main/assets/mainnet/EKrEmPnaNzgGixE61ERsTNn5oMoMqACJf3GniFpgGPbp/SkellyCoin.png","decimals":9,"address":"EKrEmPnaNzgGixE61ERsTNn5oMoMqACJf3GniFpgGPbp","chainId":101,"tags":["utility-token","community-token"],"extensions":{"website":"https://skellygang.com","twitter":"https://twitter.com/SkellyGangNFT","discord":"https://discord.gg/3T3jVtac","description":"The skelly gang utility token earned through staking your skelly gang NFTs."}}