{"name":"FuckElon","symbol":"FELON","logoURI":"https://raw.githubusercontent.com/solana-labs/token-list/main/assets/mainnet/EZqcdU8RLu9EChZgrY2BNVg8eovfdGyTiY2bd69EsPgQ/logo.png","decimals":9,"address":"EZqcdU8RLu9EChZgrY2BNVg8eovfdGyTiY2bd69EsPgQ","chainId":101,"tags":null,"extensions":{"website":"https://fuckelonmusk.godaddysites.com/","bridgeContract":null,"assetContract":null,"explorer":null,"twitter":"https://twitter.com/FuckElonMusk8","github":null,"medium":null,"tgann":null,"tggroup":null,"discord":null,"serumV3Usdt":null,"serumV3Usdc":null,"coingeckoId":null,"imageUrl":null,"description":null,"telegram":"https://t.me/joinchat/cgUOCIRSTJ9hZmY1","telegramAnnouncements":"https://t.me/fuckelonmusktoday"}}