{"name":"Sunflowers seeds","symbol":"SunS","logoURI":"https://raw.githubusercontent.com/solana-labs/token-list/main/assets/mainnet/H18JF1LhJmNqqRCxc3JaWx4KZ4ACUYeARrr1XbGyzFiD/logo.png","decimals":0,"address":"H18JF1LhJmNqqRCxc3JaWx4KZ4ACUYeARrr1XbGyzFiD","chainId":101,"tags":["meme-token","CATE","NFT","community"],"extensions":{"website":"https://anasnejb.com","bridgeContract":null,"assetContract":null,"explorer":null,"twitter":null,"github":null,"medium":null,"tgann":null,"tggroup":null,"discord":null,"serumV3Usdt":null,"serumV3Usdc":null,"coingeckoId":null,"imageUrl":null,"description":null}}