{"name":"Far-Out Token","symbol":"FAROUT","logoURI":"https://raw.githubusercontent.com/solana-labs/token-list/main/assets/mainnet/J5gLhk6mmQ4PSoir1Ufh8JY2ytEHA93YupzYiTFVCgcL/logo.png","decimals":9,"address":"J5gLhk6mmQ4PSoir1Ufh8JY2ytEHA93YupzYiTFVCgcL","chainId":101,"tags":null,"extensions":{"website":"https://gitlab.com/far-out/far-out-token","bridgeContract":null,"assetContract":null,"explorer":null,"twitter":null,"github":null,"medium":null,"tgann":null,"tggroup":null,"discord":null,"serumV3Usdt":null,"serumV3Usdc":null,"coingeckoId":null,"imageUrl":null,"description":null}}