{"name":"UUGAA","symbol":"UUGAA","logoURI":"https://raw.githubusercontent.com/gorillazmaster/UUGAA/main/logo.png","decimals":9,"address":"UUGAAWxhG2TXnyZHA4jDUaSJQQi2nf6UymtsBspRihz","chainId":101,"tags":["social-token","game-token","utility-token"],"extensions":{"website":"https://gorillazreborn.xyz","bridgeContract":null,"assetContract":null,"explorer":null,"twitter":"https://twitter.com/GorillazReborn","github":null,"medium":null,"tgann":null,"tggroup":null,"discord":"https://discord.com/invite/fHbsnvSraj","serumV3Usdt":null,"serumV3Usdc":null,"coingeckoId":null,"imageUrl":null,"description":null}}