{"name":"Hiro LaunchDAO","symbol":"HIRO","logoURI":"https://raw.githubusercontent.com/solana-labs/token-list/main/assets/mainnet/rz251Qbsa27sL8Y1H7h4qu71j6Q7ukNmskg5ZDhPCg3/logo.png","decimals":6,"address":"rz251Qbsa27sL8Y1H7h4qu71j6Q7ukNmskg5ZDhPCg3","chainId":102,"tags":null,"extensions":{"website":"https://hiro-finance.github.io/","bridgeContract":null,"assetContract":null,"explorer":null,"twitter":"https://twitter.com/HiroLaunchdao","github":null,"medium":null,"tgann":null,"tggroup":null,"discord":null,"serumV3Usdt":null,"serumV3Usdc":null,"coingeckoId":null,"imageUrl":null,"description":null}}